timebomb/__init__.py
timebomb-0.0.1.dist-info/METADATA
timebomb-0.0.1.dist-info/WHEEL
timebomb-0.0.1.dist-info/top_level.txt
timebomb-0.0.1.dist-info/RECORD
