Metadata-Version: 2.1
Name: timebomb
Version: 0.0.1
Summary: A set of utilities to 
Home-page: http://packages.python.org/timebomb
Author: Evin Sellin
Author-email: evinism@gmail.com
License: MIT
Platform: UNKNOWN
Requires-Python: ~=3.6
